compressedftir/datareader.py
compressedftir/lcurve.py
compressedftir/mp_utils.py
compressedftir/utils.py
compressedftir-0.0.3.dist-info/METADATA
compressedftir-0.0.3.dist-info/WHEEL
compressedftir-0.0.3.dist-info/top_level.txt
compressedftir-0.0.3.dist-info/RECORD
