Metadata-Version: 2.1
Name: compressedftir
Version: 0.0.3
Summary: Reconstruction of sample FTIR data
Home-page: https://github.com/manuelmarschall/CompressedFTIR
Author: Manuel Marschall
Author-email: manuelmarschall@ptb.de
License: UNKNOWN
Platform: UNKNOWN
Classifier: Programming Language :: Python :: 3
Classifier: Operating System :: OS Independent
Requires-Python: >=3.6
